kiwipy/__init__.py
kiwipy/communicate.py
kiwipy/communications.py
kiwipy/exceptions.py
kiwipy/filters.py
kiwipy/futures.py
kiwipy/local.py
kiwipy/utils.py
kiwipy/rmq/__init__.py
kiwipy/rmq/communicator.py
kiwipy/rmq/configure.py
kiwipy/rmq/defaults.py
kiwipy/rmq/messages.py
kiwipy/rmq/tasks.py
kiwipy/rmq/threadcomms.py
kiwipy/rmq/utils.py
kiwipy-0.9.0.dist-info/licenses/LICENSE.txt
kiwipy-0.9.0.dist-info/WHEEL
kiwipy-0.9.0.dist-info/METADATA
kiwipy-0.9.0.dist-info/RECORD
