Metadata-Version: 2.4
Name: kiwipy
Version: 0.9.0
Summary: Robust, high-volume, message based communication made easy.
Keywords: ommunication,messaging,rpc,broadcast
Author: Sebastiaan P. Huber, Jason Yu, Sonia Collaud
Author-email: Martin Uhrin <martin.uhrin@gmail.com>
Requires-Python: >=3.9
Classifier: Development Status :: 4 - Beta
Classifier: License :: OSI Approved :: MIT License
Classifier: License :: OSI Approved :: GNU General Public License v3 (GPLv3)
Classifier: Programming Language :: Python
Classifier: Programming Language :: Python :: 3.9
Classifier: Programming Language :: Python :: 3.10
Classifier: Programming Language :: Python :: 3.11
Classifier: Programming Language :: Python :: 3.12
Classifier: Programming Language :: Python :: 3.13
License-File: LICENSE.txt
Requires-Dist: deprecation
Requires-Dist: pyyaml~=6.0
Requires-Dist: shortuuid
Requires-Dist: docutils ; extra == "docs"
Requires-Dist: jupyter ; extra == "docs"
Requires-Dist: nbsphinx ; extra == "docs"
Requires-Dist: pandoc ; extra == "docs"
Requires-Dist: sphinx ; extra == "docs"
Requires-Dist: sphinx-autobuild ; extra == "docs"
Requires-Dist: pre-commit~=2.2 ; extra == "pre-commit"
Requires-Dist: pylint==2.12.2 ; extra == "pre-commit"
Requires-Dist: aio-pika~=9.5.0 ; extra == "rmq"
Requires-Dist: pamqp~=3.2 ; extra == "rmq"
Requires-Dist: pytray>=0.3.4,<0.4.0 ; extra == "rmq"
Requires-Dist: coverage ; extra == "tests"
Requires-Dist: ipykernel ; extra == "tests"
Requires-Dist: pytest-cov ; extra == "tests"
Requires-Dist: pytest~=7.0 ; extra == "tests"
Requires-Dist: pytest-asyncio~=0.12,<0.17 ; extra == "tests"
Requires-Dist: pytest-notebook>=0.9 ; extra == "tests"
Requires-Dist: pytest-benchmark ; extra == "tests"
Requires-Dist: pika ; extra == "tests"
Requires-Dist: msgpack ; extra == "tests"
Project-URL: Documentation, https://kiwipy.readthedocs.io
Project-URL: Home, https://github.com/aiidateam/kiwipy
Project-URL: Source, https://github.com/aiidateam/kiwipy
Provides-Extra: docs
Provides-Extra: pre-commit
Provides-Extra: rmq
Provides-Extra: tests
